omnilogic/__init__.py
omnilogic-0.6.1.dist-info/licenses/LICENCE.txt
omnilogic-0.6.1.dist-info/METADATA
omnilogic-0.6.1.dist-info/WHEEL
omnilogic-0.6.1.dist-info/top_level.txt
omnilogic-0.6.1.dist-info/RECORD
