Metadata-Version: 2.4
Name: omnilogic
Version: 0.6.1
Summary: Integration for the Hayward OmniLogic pool control system
Home-page: https://github.com/djtimca/omnilogic-api
Download-URL: https://github.com/djtimca/omnilogic-api/raw/master/dist/omnilogic-0.5.0.tar.gz
Author: Tim Empringham
Author-email: tim.empringham@live.ca
License: apache-2.0
Keywords: OmniLogic,Hayward,Pool,Spa
Classifier: Development Status :: 3 - Alpha
Classifier: Intended Audience :: Developers
Classifier: Topic :: Software Development :: Build Tools
Classifier: License :: OSI Approved :: Apache Software License
Classifier: Programming Language :: Python :: 3
Classifier: Programming Language :: Python :: 3.4
Classifier: Programming Language :: Python :: 3.5
Classifier: Programming Language :: Python :: 3.6
License-File: LICENCE.txt
Requires-Dist: xmltodict
Requires-Dist: aiohttp
Dynamic: author
Dynamic: author-email
Dynamic: classifier
Dynamic: description
Dynamic: description-content-type
Dynamic: download-url
Dynamic: home-page
Dynamic: keywords
Dynamic: license
Dynamic: license-file
Dynamic: requires-dist
Dynamic: summary
